{
  "S0": {
    "name": "\uacf5\ubd80\ud558\ub294\uc9c0\ud638 Ziho",
    "url": "https://www.youtube.com/watch?v=rXdFT3XTLsI",
    "live_status": "live",
    "concurrent_view_count": 0,
    "release_timestamp": 0,
    "icon": "https://yewtu.be/vi/rXdFT3XTLsI/mqdefault.jpg"
  },
  "S1": {
    "name": "honeystudies",
    "url": "https://www.youtube.com/watch?v=vF3r5YogvuQ",
    "live_status": "live",
    "concurrent_view_count": 0,
    "release_timestamp": 0,
    "icon": "https://yewtu.be/vi/vF3r5YogvuQ/mqdefault.jpg"
  },
  "S2": {
    "name": "Smakshi",
    "url": "https://www.youtube.com/watch?v=7Q7IPXevqQM",
    "live_status": "live",
    "concurrent_view_count": 0,
    "release_timestamp": 0,
    "icon": "https://yewtu.be/vi/7Q7IPXevqQM/mqdefault.jpg"
  },
  "S3": {
    "name": "Divit Gaur",
    "url": "https://www.youtube.com/watch?v=Q5_rSBJKPrg",
    "live_status": "live",
    "concurrent_view_count": 0,
    "release_timestamp": 0,
    "icon": "https://yewtu.be/vi/Q5_rSBJKPrg/mqdefault.jpg"
  },
  "S4": {
    "name": "Sunnie's Study Caf\u00e9",
    "url": "https://www.youtube.com/watch?v=qs8X7rD69Zc",
    "live_status": "live",
    "concurrent_view_count": 0,
    "release_timestamp": 0,
    "icon": "https://yewtu.be/vi/qs8X7rD69Zc/mqdefault.jpg"
  },
  "S5": {
    "name": "Study with Elaine",
    "url": "https://www.youtube.com/watch?v=Abh75LI5d8U",
    "live_status": "live",
    "concurrent_view_count": 0,
    "release_timestamp": 0,
    "icon": "https://yewtu.be/vi/Abh75LI5d8U/mqdefault.jpg"
  },
  "S6": {
    "name": "SeewhY",
    "url": "https://www.youtube.com/watch?v=JBcjGTLqtRU",
    "live_status": "live",
    "concurrent_view_count": 0,
    "release_timestamp": 0,
    "icon": "https://yewtu.be/vi/JBcjGTLqtRU/mqdefault.jpg"
  },
  "S7": {
    "name": "Lost in Awww",
    "url": "https://www.youtube.com/watch?v=rMG3eig2Bto",
    "live_status": "live",
    "concurrent_view_count": 0,
    "release_timestamp": 0,
    "icon": "https://yewtu.be/vi/rMG3eig2Bto/mqdefault.jpg"
  },
  "S8": {
    "name": "MEDGIRL \ud83e\ude7a",
    "url": "https://www.youtube.com/watch?v=01CRP5gPGtE",
    "live_status": "live",
    "concurrent_view_count": 0,
    "release_timestamp": 0,
    "icon": "https://yewtu.be/vi/01CRP5gPGtE/mqdefault.jpg"
  },
  "S9": {
    "name": "PYQ NEET-JEE Live",
    "url": "https://www.youtube.com/watch?v=TAy76Mn2pbg",
    "live_status": "live",
    "concurrent_view_count": 0,
    "release_timestamp": 0,
    "icon": "https://yewtu.be/vi/TAy76Mn2pbg/mqdefault.jpg"
  },
  "S10": {
    "name": "Jazz Cafe Ambience",
    "url": "https://www.youtube.com/watch?v=0vrbVzEOsSA",
    "live_status": "live",
    "concurrent_view_count": 0,
    "release_timestamp": 0,
    "icon": "https://yewtu.be/vi/0vrbVzEOsSA/mqdefault.jpg"
  },
  "S11": {
    "name": "MEDGUY",
    "url": "https://www.youtube.com/watch?v=wM_e_1PlRfk",
    "live_status": "live",
    "concurrent_view_count": 0,
    "release_timestamp": 0,
    "icon": "https://yewtu.be/vi/wM_e_1PlRfk/mqdefault.jpg"
  },
  "S12": {
    "name": "MK Shaon",
    "url": "https://www.youtube.com/watch?v=L0BGOpA1qtA",
    "live_status": "live",
    "concurrent_view_count": 0,
    "release_timestamp": 0,
    "icon": "https://yewtu.be/vi/L0BGOpA1qtA/mqdefault.jpg"
  },
  "S13": {
    "name": "Yashwant Kumar Live Study",
    "url": "https://www.youtube.com/watch?v=7atVMoyS9P4",
    "live_status": "live",
    "concurrent_view_count": 0,
    "release_timestamp": 0,
    "icon": "https://yewtu.be/vi/7atVMoyS9P4/mqdefault.jpg"
  },
  "S14": {
    "name": "Sleepy Legend ASMR [EN]",
    "url": "https://www.youtube.com/watch?v=q4999XcpSKU",
    "live_status": "live",
    "concurrent_view_count": 0,
    "release_timestamp": 0,
    "icon": "https://yewtu.be/vi/q4999XcpSKU/mqdefault.jpg"
  },
  "S15": {
    "name": "Dhruvika kothari",
    "url": "https://www.youtube.com/watch?v=5qhj70dvdkY",
    "live_status": "live",
    "concurrent_view_count": 0,
    "release_timestamp": 0,
    "icon": "https://yewtu.be/vi/5qhj70dvdkY/mqdefault.jpg"
  },
  "S16": {
    "name": "Education learner Point",
    "url": "https://www.youtube.com/watch?v=i3YXv4UmHMs",
    "live_status": "live",
    "concurrent_view_count": 0,
    "release_timestamp": 0,
    "icon": "https://yewtu.be/vi/i3YXv4UmHMs/mqdefault.jpg"
  },
  "S17": {
    "name": "Wake-up-stranger",
    "url": "https://www.youtube.com/watch?v=hOa9qp9--YM",
    "live_status": "live",
    "concurrent_view_count": 0,
    "release_timestamp": 0,
    "icon": "https://yewtu.be/vi/hOa9qp9--YM/mqdefault.jpg"
  },
  "S18": {
    "name": "Dr Prerana Somra",
    "url": "https://www.youtube.com/watch?v=qM438OzQdkQ",
    "live_status": "live",
    "concurrent_view_count": 0,
    "release_timestamp": 0,
    "icon": "https://yewtu.be/vi/qM438OzQdkQ/mqdefault.jpg"
  },
  "S19": {
    "name": "StudyWithMe",
    "url": "https://www.youtube.com/watch?v=ZHBvMaMCrhM",
    "live_status": "live",
    "concurrent_view_count": 0,
    "release_timestamp": 0,
    "icon": "https://yewtu.be/vi/ZHBvMaMCrhM/mqdefault.jpg"
  }
}