{"S4": {"name": "\u30aa\u30f3\u30e9\u30a4\u30f3\u4f5c\u696d\u90e8\u5c4b", "url": "https://raw.githubusercontent.com/JamyJones/Pastebin/main/assets/S4.gif", "live_status": "is_live", "concurrent_view_count": 84, "release_timestamp": 1666669395, "icon": "https://i.ytimg.com/vi/AvGbepg86JA/maxresdefault.jpg"}, "S5": {"name": "Taro's Classroom", "url": "https://raw.githubusercontent.com/JamyJones/Pastebin/main/assets/S5.gif", "live_status": "is_live", "concurrent_view_count": 68, "release_timestamp": 1745588293, "icon": "https://i.ytimg.com/vi/RUeyffv3NOo/maxresdefault.jpg"}, "S6": {"name": "Twinkle - Study With Me", "url": "https://raw.githubusercontent.com/JamyJones/Pastebin/main/assets/S6.gif", "live_status": "is_live", "concurrent_view_count": 60, "release_timestamp": 1745548432, "icon": "https://i.ytimg.com/vi/Pw3W0ctNIiE/maxresdefault.jpg"}, "S7": {"name": "living better", "url": "https://raw.githubusercontent.com/JamyJones/Pastebin/main/assets/S7.gif", "live_status": "is_live", "concurrent_view_count": 62, "release_timestamp": 1745577066, "icon": "https://i.ytimg.com/vi/owVX0p-iV-w/maxresdefault.jpg"}, "S8": {"name": "MEDGIRL \ud83e\ude7a", "url": "https://raw.githubusercontent.com/JamyJones/Pastebin/main/assets/S8.gif", "live_status": "is_live", "concurrent_view_count": 56, "release_timestamp": 1744481337, "icon": "https://i.ytimg.com/vi/W2FJsPyGrr0/maxresdefault.jpg"}, "S9": {"name": "\ub0b4\ud798\ub4e4\ub2e4", "url": "https://raw.githubusercontent.com/JamyJones/Pastebin/main/assets/S9.gif", "live_status": "is_live", "concurrent_view_count": 45, "release_timestamp": 1745532426, "icon": "https://i.ytimg.com/vi/6JbLQLQdOZU/maxresdefault.jpg"}, "S10": {"name": "Tina Lin\u2019s database \ud83d\udcf7", "url": "https://raw.githubusercontent.com/JamyJones/Pastebin/main/assets/S10.gif", "live_status": "is_live", "concurrent_view_count": 38, "release_timestamp": 1742872247, "icon": "https://i.ytimg.com/vi/XK4u0IDUJeE/maxresdefault.jpg"}, "S11": {"name": "Tris SH", "url": "https://raw.githubusercontent.com/JamyJones/Pastebin/main/assets/S11.gif", "live_status": "is_live", "concurrent_view_count": 32, "release_timestamp": 1745565684, "icon": "https://i.ytimg.com/vi/8qSVBLgaLyk/maxresdefault.jpg"}, "S12": {"name": "Nerdy Tales", "url": "https://raw.githubusercontent.com/JamyJones/Pastebin/main/assets/S12.gif", "live_status": "is_live", "concurrent_view_count": 31, "release_timestamp": 1745586178, "icon": "https://i.ytimg.com/vi/5HP38IYOS2A/maxresdefault.jpg"}, "S13": {"name": "Ahmed\u2019s Study Zone", "url": "https://raw.githubusercontent.com/JamyJones/Pastebin/main/assets/S13.gif", "live_status": "is_live", "concurrent_view_count": 29, "release_timestamp": 1745578871, "icon": "https://i.ytimg.com/vi/3ulq_bvvGxc/maxresdefault.jpg"}, "S14": {"name": "SMStudy", "url": "https://raw.githubusercontent.com/JamyJones/Pastebin/main/assets/S14.gif", "live_status": "is_live", "concurrent_view_count": 31, "release_timestamp": 1745583576, "icon": "https://i.ytimg.com/vi/Y1E3XRdKy4Q/hqdefault.jpg?v=680b71af"}, "S15": {"name": "Hilary - Study With Me", "url": "https://raw.githubusercontent.com/JamyJones/Pastebin/main/assets/S15.gif", "live_status": "is_live", "concurrent_view_count": 25, "release_timestamp": 1740999688, "icon": "https://i.ytimg.com/vi/sEGOogpgm_c/maxresdefault.jpg"}, "S16": {"name": "\uafb8\uc900\ub9e8 \ubd80\ub9e8 steady Boo_man", "url": "https://raw.githubusercontent.com/JamyJones/Pastebin/main/assets/S16.gif", "live_status": "is_live", "concurrent_view_count": 25, "release_timestamp": 1745542401, "icon": "https://i.ytimg.com/vi/7V-JMWbS2M0/maxresdefault.jpg"}, "S17": {"name": "Study with Sabrina", "url": "https://raw.githubusercontent.com/JamyJones/Pastebin/main/assets/S17.gif", "live_status": "is_live", "concurrent_view_count": 26, "release_timestamp": 1745580784, "icon": "https://i.ytimg.com/vi/Ofr-NE_e3mw/maxresdefault.jpg"}, "S18": {"name": "Dr Prerana Somra", "url": "https://raw.githubusercontent.com/JamyJones/Pastebin/main/assets/S18.gif", "live_status": "is_live", "concurrent_view_count": 25, "release_timestamp": 1745545511, "icon": "https://i.ytimg.com/vi/1M_SpHrDANc/maxresdefault.jpg"}, "S19": {"name": "\uc774\ube10 enliven", "url": "https://raw.githubusercontent.com/JamyJones/Pastebin/main/assets/S19.gif", "live_status": "is_live", "concurrent_view_count": 25, "release_timestamp": 1745572657, "icon": "https://i.ytimg.com/vi/yCNLoPV5ycg/hqdefault.jpg?v=680b5324"}, "S20": {"name": "Ema", "url": "https://raw.githubusercontent.com/JamyJones/Pastebin/main/assets/S20.gif", "live_status": "is_live", "concurrent_view_count": 22, "release_timestamp": 1745589321, "icon": "https://i.ytimg.com/vi/Wk1XwlGaD5U/maxresdefault.jpg"}, "S21": {"name": "Alexander Mayhue", "url": "https://raw.githubusercontent.com/JamyJones/Pastebin/main/assets/S21.gif", "live_status": "is_live", "concurrent_view_count": 19, "release_timestamp": 1743870536, "icon": "https://i.ytimg.com/vi/DjeSLIiveVc/maxresdefault.jpg"}, "S22": {"name": "I hate studying", "url": "https://raw.githubusercontent.com/JamyJones/Pastebin/main/assets/S22.gif", "live_status": "is_live", "concurrent_view_count": 17, "release_timestamp": 1745586163, "icon": "https://i.ytimg.com/vi/o8ZqtOiVdXE/maxresdefault.jpg"}, "S23": {"name": "Study Monkers", "url": "https://raw.githubusercontent.com/JamyJones/Pastebin/main/assets/S23.gif", "live_status": "is_live", "concurrent_view_count": 16, "release_timestamp": 1745591795, "icon": "https://i.ytimg.com/vi/5BpI5w6eTgE/maxresdefault.jpg"}, "S24": {"name": "Brother akku lalit", "url": "https://raw.githubusercontent.com/JamyJones/Pastebin/main/assets/S24.gif", "live_status": "is_live", "concurrent_view_count": 9, "release_timestamp": 1745590386, "icon": "https://i.ytimg.com/vi/ytinyRsy9io/maxresdefault.jpg"}, "S25": {"name": "Sons Serenos", "url": "https://raw.githubusercontent.com/JamyJones/Pastebin/main/assets/S25.gif", "live_status": "is_live", "concurrent_view_count": 16, "release_timestamp": 1745577033, "icon": "https://i.ytimg.com/vi/MU8ICEqORNY/maxresdefault.jpg"}, "S26": {"name": "Essential New York", "url": "https://raw.githubusercontent.com/JamyJones/Pastebin/main/assets/S26.gif", "live_status": "is_live", "concurrent_view_count": 12, "release_timestamp": 1744258437, "icon": "https://i.ytimg.com/vi/flHmQStenm8/maxresdefault.jpg"}, "S27": {"name": "ipl", "url": "https://raw.githubusercontent.com/JamyJones/Pastebin/main/assets/S27.gif", "live_status": "is_live", "concurrent_view_count": 10, "release_timestamp": 1745592198, "icon": "https://i.ytimg.com/vi/5oESE_Z8hIk/maxresdefault.jpg"}, "S28": {"name": "venus\u2019 study journal", "url": "https://raw.githubusercontent.com/JamyJones/Pastebin/main/assets/S28.gif", "live_status": "is_live", "concurrent_view_count": 11, "release_timestamp": 1745589664, "icon": "https://i.ytimg.com/vi/Q8h4raw5NHo/maxresdefault.jpg"}, "S29": {"name": "chreee.e", "url": "https://raw.githubusercontent.com/JamyJones/Pastebin/main/assets/S29.gif", "live_status": "is_live", "concurrent_view_count": 8, "release_timestamp": 1745583591, "icon": "https://i.ytimg.com/vi/6VoxjRXT28o/maxresdefault.jpg"}, "S30": {"name": "Study with Elaine", "url": "https://raw.githubusercontent.com/JamyJones/Pastebin/main/assets/S30.gif", "live_status": "is_live", "concurrent_view_count": 10, "release_timestamp": 1745418566, "icon": "https://i.ytimg.com/vi/Qw-yBeWAkO8/maxresdefault.jpg"}, "S31": {"name": "SAJAJ /\u0633\u062c\u0627\u062c", "url": "https://raw.githubusercontent.com/JamyJones/Pastebin/main/assets/S31.gif", "live_status": "is_live", "concurrent_view_count": 8, "release_timestamp": 1745559536, "icon": "https://i.ytimg.com/vi/1JSEJEi7Obg/hqdefault.jpg?v=680b1fd5"}, "S32": {"name": "Md Raiyan Islam", "url": "https://raw.githubusercontent.com/JamyJones/Pastebin/main/assets/S32.gif", "live_status": "is_live", "concurrent_view_count": 5, "release_timestamp": 1745586345, "icon": "https://i.ytimg.com/vi/rAO0OXIAhBA/hqdefault.jpg?v=680b8829"}, "S33": {"name": "Studyistic", "url": "https://raw.githubusercontent.com/JamyJones/Pastebin/main/assets/S33.gif", "live_status": "is_live", "concurrent_view_count": 13, "release_timestamp": 1732818356, "icon": "https://i.ytimg.com/vi/1OtdnQEVqG8/maxresdefault.jpg"}, "S34": {"name": "Olivia \uc62c\ub9ac\ube44\uc544", "url": "https://raw.githubusercontent.com/JamyJones/Pastebin/main/assets/S34.gif", "live_status": "is_live", "concurrent_view_count": 10, "release_timestamp": 1745586191, "icon": "https://i.ytimg.com/vi/Qov9bNeQP2c/maxresdefault.jpg"}, "S35": {"name": "\u0623\u0633\u0640\u0640\u0640\u0627\u0645\u0640\u0640\u0640\u0629", "url": "https://raw.githubusercontent.com/JamyJones/Pastebin/main/assets/S35.gif", "live_status": "is_live", "concurrent_view_count": 10, "release_timestamp": 1745578971, "icon": "https://i.ytimg.com/vi/Iyfa4Fiu4lI/maxresdefault.jpg"}, "S36": {"name": "\ud835\udc09\ud835\udc2e\ud835\udc27\ud835\udc2b\ud835\udc1a\ud835\udc20\ud835\udc21\ud835\udc1a\ud835\udc1d", "url": "https://raw.githubusercontent.com/JamyJones/Pastebin/main/assets/S36.gif", "live_status": "is_live", "concurrent_view_count": 5, "release_timestamp": 1745589811, "icon": "https://i.ytimg.com/vi/rAkK-zl5fFE/maxresdefault.jpg"}, "S37": {"name": "\ud560 \uc218 \uc788\ub2e4 [PRINCE]", "url": "https://raw.githubusercontent.com/JamyJones/Pastebin/main/assets/S37.gif", "live_status": "is_live", "concurrent_view_count": 5, "release_timestamp": 1745554846, "icon": "https://i.ytimg.com/vi/NlLU_-miAFk/maxresdefault.jpg"}, "S38": {"name": "Addy Corner", "url": "https://raw.githubusercontent.com/JamyJones/Pastebin/main/assets/S38.gif", "live_status": "is_live", "concurrent_view_count": 9, "release_timestamp": 1745555203, "icon": "https://i.ytimg.com/vi/YF1pGM4wykk/maxresdefault.jpg"}, "S39": {"name": "MedGirl", "url": "https://raw.githubusercontent.com/JamyJones/Pastebin/main/assets/S39.gif", "live_status": "is_live", "concurrent_view_count": 4, "release_timestamp": 1745578969, "icon": "https://i.ytimg.com/vi/B2mOEHXLs3M/maxresdefault.jpg"}, "S40": {"name": "Shashank Singh", "url": "https://raw.githubusercontent.com/JamyJones/Pastebin/main/assets/S40.gif", "live_status": "is_live", "concurrent_view_count": 5, "release_timestamp": 1745587045, "icon": "https://i.ytimg.com/vi/hIREpxjTK6A/maxresdefault.jpg"}, "S41": {"name": "\u0639\u0644\u064a", "url": "https://raw.githubusercontent.com/JamyJones/Pastebin/main/assets/S41.gif", "live_status": "is_live", "concurrent_view_count": 7, "release_timestamp": 1745587572, "icon": "https://i.ytimg.com/vi/TYy5Q6wK2-g/maxresdefault.jpg"}, "S42": {"name": "Wake-up-stranger", "url": "https://raw.githubusercontent.com/JamyJones/Pastebin/main/assets/S42.gif", "live_status": "is_live", "concurrent_view_count": 8, "release_timestamp": 1745546057, "icon": "https://i.ytimg.com/vi/AoIMup-XUyg/maxresdefault.jpg"}, "S43": {"name": "Pratik FR", "url": "https://raw.githubusercontent.com/JamyJones/Pastebin/main/assets/S43.gif", "live_status": "is_live", "concurrent_view_count": 6, "release_timestamp": 1745581540, "icon": "https://i.ytimg.com/vi/8k0XhG6j0dk/maxresdefault.jpg"}, "S44": {"name": "Max Team", "url": "https://raw.githubusercontent.com/JamyJones/Pastebin/main/assets/S44.gif", "live_status": "is_live", "concurrent_view_count": 4, "release_timestamp": 1745591205, "icon": "https://i.ytimg.com/vi/qW6K7_FmsfA/maxresdefault.jpg"}, "S45": {"name": "Neelam\ud83e\ude7a", "url": "https://raw.githubusercontent.com/JamyJones/Pastebin/main/assets/S45.gif", "live_status": "is_live", "concurrent_view_count": 6, "release_timestamp": 1745580749, "icon": "https://i.ytimg.com/vi/achi4AK5wNc/maxresdefault.jpg"}, "S46": {"name": "Calm And Caffeine", "url": "https://raw.githubusercontent.com/JamyJones/Pastebin/main/assets/S46.gif", "live_status": "is_live", "concurrent_view_count": 6, "release_timestamp": 1745573558, "icon": "https://i.ytimg.com/vi/E6ydrvo6TOY/hqdefault.jpg?v=680b56a8"}, "S47": {"name": "7ayussh", "url": "https://raw.githubusercontent.com/JamyJones/Pastebin/main/assets/S47.gif", "live_status": "is_live", "concurrent_view_count": 5, "release_timestamp": 1745579493, "icon": "https://i.ytimg.com/vi/kjlZ7WA8hP0/maxresdefault.jpg"}, "S48": {"name": "izzKK", "url": "https://raw.githubusercontent.com/JamyJones/Pastebin/main/assets/S48.gif", "live_status": "is_live", "concurrent_view_count": 4, "release_timestamp": 1745585896, "icon": "https://i.ytimg.com/vi/D1dqvHRVabY/maxresdefault.jpg"}, "S49": {"name": "study with nooreldean", "url": "https://raw.githubusercontent.com/JamyJones/Pastebin/main/assets/S49.gif", "live_status": "is_live", "concurrent_view_count": 6, "release_timestamp": 1745581120, "icon": "https://i.ytimg.com/vi/bRZCxXxATa4/maxresdefault.jpg"}, "S50": {"name": "Masked Medic", "url": "https://raw.githubusercontent.com/JamyJones/Pastebin/main/assets/S50.gif", "live_status": "is_live", "concurrent_view_count": 6, "release_timestamp": 1745592100, "icon": "https://i.ytimg.com/vi/BpuP3kAY_OM/hqdefault.jpg?v=680b9f17"}, "S51": {"name": "\uacf5\ubd80\ud558\ub294\uc9c0\ud638 Ziho", "url": "https://raw.githubusercontent.com/JamyJones/Pastebin/main/assets/S51.gif", "live_status": "is_live", "concurrent_view_count": 37, "release_timestamp": 1745592888, "icon": "https://i.ytimg.com/vi/MICbxj-Ohfk/maxresdefault.jpg"}, "S52": {"name": "studytimemd", "url": "https://raw.githubusercontent.com/JamyJones/Pastebin/main/assets/S52.gif", "live_status": "is_live", "concurrent_view_count": 1, "release_timestamp": 1745584548, "icon": "https://i.ytimg.com/vi/R4M1uGg_6gU/maxresdefault.jpg"}, "S53": {"name": "sarimasalambasi", "url": "https://raw.githubusercontent.com/JamyJones/Pastebin/main/assets/S53.gif", "live_status": "is_live", "concurrent_view_count": 4, "release_timestamp": 1745585515, "icon": "https://i.ytimg.com/vi/mRPErd59CXk/maxresdefault.jpg"}, "S54": {"name": "Study With Pomodoro technique", "url": "https://raw.githubusercontent.com/JamyJones/Pastebin/main/assets/S54.gif", "live_status": "is_live", "concurrent_view_count": 4, "release_timestamp": 1745587892, "icon": "https://i.ytimg.com/vi/OoltXeB0JUY/maxresdefault.jpg"}, "S55": {"name": "just-Nico", "url": "https://raw.githubusercontent.com/JamyJones/Pastebin/main/assets/S55.gif", "live_status": "is_live", "concurrent_view_count": 4, "release_timestamp": 1744162075, "icon": "https://i.ytimg.com/vi/OCqMiZCOSus/maxresdefault.jpg"}, "S56": {"name": "Erik Riekert", "url": "https://raw.githubusercontent.com/JamyJones/Pastebin/main/assets/S56.gif", "live_status": "is_live", "concurrent_view_count": 4, "release_timestamp": 1745582746, "icon": "https://i.ytimg.com/vi/fir7MFXkBek/maxresdefault.jpg"}, "S57": {"name": "Sangam Kumar", "url": "https://raw.githubusercontent.com/JamyJones/Pastebin/main/assets/S57.gif", "live_status": "is_live", "concurrent_view_count": 5, "release_timestamp": 1745556513, "icon": "https://i.ytimg.com/vi/KTUcpieEB-g/maxresdefault.jpg"}, "S58": {"name": "\u3053\u305f\u30af\u30ed", "url": "https://raw.githubusercontent.com/JamyJones/Pastebin/main/assets/S58.gif", "live_status": "is_live", "concurrent_view_count": 3, "release_timestamp": 1745549383, "icon": "https://i.ytimg.com/vi/Gcukufov3J4/maxresdefault.jpg"}, "S59": {"name": "Study with Luke Skyward", "url": "https://raw.githubusercontent.com/JamyJones/Pastebin/main/assets/S59.gif", "live_status": "is_live", "concurrent_view_count": 2, "release_timestamp": 1745589838, "icon": "https://i.ytimg.com/vi/TRNwy3boOFk/hqdefault.jpg?v=680b9643"}, "S60": {"name": "kunal tiwary", "url": "https://raw.githubusercontent.com/JamyJones/Pastebin/main/assets/S60.gif", "live_status": "is_live", "concurrent_view_count": 1, "release_timestamp": 1745585315, "icon": "https://i.ytimg.com/vi/YxxHGtt3E5E/maxresdefault.jpg"}, "S61": {"name": "Study with danbia", "url": "https://raw.githubusercontent.com/JamyJones/Pastebin/main/assets/S61.gif", "live_status": "is_live", "concurrent_view_count": 1, "release_timestamp": 1745579666, "icon": "https://i.ytimg.com/vi/Kuetw8d2_EU/hqdefault.jpg?v=680ad256"}, "S62": {"name": "Samyak Aditya", "url": "https://raw.githubusercontent.com/JamyJones/Pastebin/main/assets/S62.gif", "live_status": "is_live", "concurrent_view_count": 4, "release_timestamp": 1745585816, "icon": "https://i.ytimg.com/vi/cWnpBbtASDc/maxresdefault.jpg"}, "S63": {"name": "Prepare With Rahul", "url": "https://raw.githubusercontent.com/JamyJones/Pastebin/main/assets/S63.gif", "live_status": "is_live", "concurrent_view_count": 2, "release_timestamp": 1745575116, "icon": "https://i.ytimg.com/vi/ZrwMtNfORmE/hqdefault.jpg?v=680a707f"}, "S64": {"name": "StudywithVandu", "url": "https://raw.githubusercontent.com/JamyJones/Pastebin/main/assets/S64.gif", "live_status": "is_live", "concurrent_view_count": 3, "release_timestamp": 1745586375, "icon": "https://i.ytimg.com/vi/RGxnPoIaqLg/maxresdefault.jpg"}, "S65": {"name": "STUDY BO", "url": "https://raw.githubusercontent.com/JamyJones/Pastebin/main/assets/S65.gif", "live_status": "is_live", "concurrent_view_count": 2, "release_timestamp": 1745070249, "icon": "https://i.ytimg.com/vi/wkPZu21Gipk/maxresdefault.jpg"}, "S66": {"name": "Study w/jcobwhy", "url": "https://raw.githubusercontent.com/JamyJones/Pastebin/main/assets/S66.gif", "live_status": "is_live", "concurrent_view_count": 2, "release_timestamp": 1745578648, "icon": "https://i.ytimg.com/vi/bYCpFEfN2RY/maxresdefault.jpg"}, "S67": {"name": "Leo-T Tran", "url": "https://raw.githubusercontent.com/JamyJones/Pastebin/main/assets/S67.gif", "live_status": "is_live", "concurrent_view_count": 3, "release_timestamp": 1745586396, "icon": "https://i.ytimg.com/vi/N0idzFt5vM4/maxresdefault.jpg"}, "S68": {"name": "Inspector Dabas", "url": "https://raw.githubusercontent.com/JamyJones/Pastebin/main/assets/S68.gif", "live_status": "is_live", "concurrent_view_count": 6, "release_timestamp": 1745591977, "icon": "https://i.ytimg.com/vi/WRgx7dd9oVU/maxresdefault.jpg"}, "S69": {"name": "Safar UPSC Kaa", "url": "https://raw.githubusercontent.com/JamyJones/Pastebin/main/assets/S69.gif", "live_status": "is_live", "concurrent_view_count": 3, "release_timestamp": 1745575142, "icon": "https://i.ytimg.com/vi/U_wYI0nEDLQ/maxresdefault.jpg"}, "S70": {"name": "Study Brew_neetpg25", "url": "https://raw.githubusercontent.com/JamyJones/Pastebin/main/assets/S70.gif", "live_status": "is_live", "concurrent_view_count": 2, "release_timestamp": 1745581360, "icon": "https://i.ytimg.com/vi/wQM43X4jHtA/maxresdefault.jpg"}, "S71": {"name": "Hamid_StudyTogether", "url": "https://raw.githubusercontent.com/JamyJones/Pastebin/main/assets/S71.gif", "live_status": "is_live", "concurrent_view_count": 2, "release_timestamp": 1745586539, "icon": "https://i.ytimg.com/vi/-sQPkAQzpco/hqdefault.jpg?v=680b8961"}, "S72": {"name": "Wayne Austria", "url": "https://raw.githubusercontent.com/JamyJones/Pastebin/main/assets/S72.gif", "live_status": "is_live", "concurrent_view_count": 3, "release_timestamp": 1745551691, "icon": "https://i.ytimg.com/vi/YfA2pP_xLiU/maxresdefault.jpg"}, "S73": {"name": "\u03a4\u03b6\u03bf\u03bd", "url": "https://raw.githubusercontent.com/JamyJones/Pastebin/main/assets/S73.gif", "live_status": "is_live", "concurrent_view_count": 1, "release_timestamp": 1745559246, "icon": "https://i.ytimg.com/vi/ma_6k4mFxzE/maxresdefault.jpg"}, "S74": {"name": "Tharushi Wickramasinghe \ud83e\ude75", "url": "https://raw.githubusercontent.com/JamyJones/Pastebin/main/assets/S74.gif", "live_status": "is_live", "concurrent_view_count": 2, "release_timestamp": 1745585032, "icon": "https://i.ytimg.com/vi/pL_F5zHzbIk/maxresdefault.jpg"}, "S75": {"name": "Yasmine Study", "url": "https://raw.githubusercontent.com/JamyJones/Pastebin/main/assets/S75.gif", "live_status": "is_live", "concurrent_view_count": 1, "release_timestamp": 1736243010, "icon": "https://i.ytimg.com/vi/uGMSiGFc4yc/hqdefault.jpg?v=677cf48b"}, "S76": {"name": "Vikram's Journey", "url": "https://raw.githubusercontent.com/JamyJones/Pastebin/main/assets/S76.gif", "live_status": "is_live", "concurrent_view_count": 1, "release_timestamp": 1745574088, "icon": "https://i.ytimg.com/vi/8IWYKJaIHGs/maxresdefault.jpg"}, "S77": {"name": "Perk Up", "url": "https://raw.githubusercontent.com/JamyJones/Pastebin/main/assets/S77.gif", "live_status": "is_live", "concurrent_view_count": 1, "release_timestamp": 1745562885, "icon": "https://i.ytimg.com/vi/seaOs0j4NA0/maxresdefault.jpg"}, "S79": {"name": "Bento Study \u30d9\u30f3\u30c8", "url": "https://raw.githubusercontent.com/JamyJones/Pastebin/main/assets/S79.gif", "live_status": "is_live", "concurrent_view_count": 1, "release_timestamp": 1741190911, "icon": "https://i.ytimg.com/vi/QOVa-8ZFyCI/maxresdefault.jpg"}, "S80": {"name": "New Raghav", "url": "https://raw.githubusercontent.com/JamyJones/Pastebin/main/assets/S80.gif", "live_status": "is_live", "concurrent_view_count": 1, "release_timestamp": 1745573046, "icon": "https://i.ytimg.com/vi/PF8UxYi70nM/maxresdefault.jpg"}, "S81": {"name": "Ashu LIVE", "url": "https://raw.githubusercontent.com/JamyJones/Pastebin/main/assets/S81.gif", "live_status": "is_live", "concurrent_view_count": 1, "release_timestamp": 1745591677, "icon": "https://i.ytimg.com/vi/pG3XNxRwKEU/maxresdefault.jpg"}, "S82": {"name": "Mirin", "url": "https://raw.githubusercontent.com/JamyJones/Pastebin/main/assets/S82.gif", "live_status": "is_live", "concurrent_view_count": 1, "release_timestamp": 1745559251, "icon": "https://i.ytimg.com/vi/ZkCHbhOixJc/hqdefault.jpg?v=680b1eb5"}, "S83": {"name": "Tokyo Night Girl #Lofi", "url": "https://raw.githubusercontent.com/JamyJones/Pastebin/main/assets/S83.gif", "live_status": "is_live", "concurrent_view_count": 1, "release_timestamp": 1745013222, "icon": "https://i.ytimg.com/vi/M8b40DB24Gs/hqdefault.jpg?v=6802c990"}, "S84": {"name": "BiSMillah iAS ACADEMY \ud83d\udcbb", "url": "https://raw.githubusercontent.com/JamyJones/Pastebin/main/assets/S84.gif", "live_status": "is_live", "concurrent_view_count": 1, "release_timestamp": 1745592406, "icon": "https://i.ytimg.com/vi/agsdSGTpVt8/hqdefault.jpg?v=680ba03c"}, "S85": {"name": "MedMindsetDr", "url": "https://raw.githubusercontent.com/JamyJones/Pastebin/main/assets/S85.gif", "live_status": "is_live", "concurrent_view_count": 1, "release_timestamp": 1745572087, "icon": "https://i.ytimg.com/vi/_JwbQXDcw64/hqdefault.jpg"}, "S88": {"name": "Shaurya Swarup", "url": "https://raw.githubusercontent.com/JamyJones/Pastebin/main/assets/S88.gif", "live_status": "is_live", "concurrent_view_count": 1, "release_timestamp": 1745581202, "icon": "https://i.ytimg.com/vi/YxkVH8o4sCw/maxresdefault.jpg"}, "S89": {"name": "SMG", "url": "https://raw.githubusercontent.com/JamyJones/Pastebin/main/assets/S89.gif", "live_status": "is_live", "concurrent_view_count": 1, "release_timestamp": 1745587856, "icon": "https://i.ytimg.com/vi/QrpBvvi8A1A/maxresdefault.jpg"}, "S90": {"name": "Dra. Emma Cruz | NerdyDoc: Estudia Aprende Escribe", "url": "https://raw.githubusercontent.com/JamyJones/Pastebin/main/assets/S90.gif", "live_status": "is_live", "concurrent_view_count": 1, "release_timestamp": 1745559356, "icon": "https://i.ytimg.com/vi/LJbCkwJMWnY/maxresdefault.jpg"}, "S91": {"name": "\uc548\uae30\uc068", "url": "https://raw.githubusercontent.com/JamyJones/Pastebin/main/assets/S91.gif", "live_status": "is_live", "concurrent_view_count": 1, "release_timestamp": 1745586030, "icon": "https://i.ytimg.com/vi/16tj5EHUs28/maxresdefault.jpg"}, "S92": {"name": "Alohomora Productivity", "url": "https://raw.githubusercontent.com/JamyJones/Pastebin/main/assets/S92.gif", "live_status": "is_live", "concurrent_view_count": 1, "release_timestamp": 1745591376, "icon": "https://i.ytimg.com/vi/6efYj_GltrE/maxresdefault.jpg"}, "S93": {"name": "Cloudtone lofi", "url": "https://raw.githubusercontent.com/JamyJones/Pastebin/main/assets/S93.gif", "live_status": "is_live", "concurrent_view_count": 1, "release_timestamp": 1745591197, "icon": "https://i.ytimg.com/vi/J-mghOVtblM/maxresdefault.jpg"}, "S94": {"name": "RAM CHARIT", "url": "https://raw.githubusercontent.com/JamyJones/Pastebin/main/assets/S94.gif", "live_status": "is_live", "concurrent_view_count": 1, "release_timestamp": 1745568459, "icon": "https://i.ytimg.com/vi/B_Jtvmacikg/maxresdefault.jpg"}}