{"S0": {"name": "Pascal Zoels", "url": "https://raw.githubusercontent.com/JamyJones/Pastebin/main/assets/S0.gif", "live_status": "is_live", "concurrent_view_count": 338, "release_timestamp": 1743024195, "icon": "https://i.ytimg.com/vi/KVyRQNIIwSU/maxresdefault.jpg"}, "S1": {"name": "MEDGUY", "url": "https://raw.githubusercontent.com/JamyJones/Pastebin/main/assets/S1.gif", "live_status": "is_live", "concurrent_view_count": 268, "release_timestamp": 1742984690, "icon": "https://i.ytimg.com/vi/n3id21XMVQ0/maxresdefault.jpg"}, "S2": {"name": "Mohareb Study", "url": "https://raw.githubusercontent.com/JamyJones/Pastebin/main/assets/S2.gif", "live_status": "is_live", "concurrent_view_count": 68, "release_timestamp": 1743014463, "icon": "https://i.ytimg.com/vi/yL5fktCauDw/maxresdefault.jpg"}, "S3": {"name": "Study with Laura", "url": "https://raw.githubusercontent.com/JamyJones/Pastebin/main/assets/S3.gif", "live_status": "is_live", "concurrent_view_count": 84, "release_timestamp": 1743018112, "icon": "https://i.ytimg.com/vi/b6E--IxcQHU/maxresdefault.jpg"}, "S4": {"name": "\uacf5\ubd80\ud558\ub294\uc9c0\ud638 Ziho", "url": "https://raw.githubusercontent.com/JamyJones/Pastebin/main/assets/S4.gif", "live_status": "is_live", "concurrent_view_count": 54, "release_timestamp": 1743000778, "icon": "https://i.ytimg.com/vi/CyTdeY3vTp4/maxresdefault.jpg"}, "S5": {"name": "Hilary - Study With Me", "url": "https://raw.githubusercontent.com/JamyJones/Pastebin/main/assets/S5.gif", "live_status": "is_live", "concurrent_view_count": 17, "release_timestamp": 1740999688, "icon": "https://i.ytimg.com/vi/sEGOogpgm_c/maxresdefault.jpg"}, "S6": {"name": "Taro's Classroom", "url": "https://raw.githubusercontent.com/JamyJones/Pastebin/main/assets/S6.gif", "live_status": "is_live", "concurrent_view_count": 26, "release_timestamp": 1742951744, "icon": "https://i.ytimg.com/vi/xgVxrskkFaE/maxresdefault.jpg"}, "S7": {"name": "Tina Lin\u2019s database \ud83d\udcf7", "url": "https://raw.githubusercontent.com/JamyJones/Pastebin/main/assets/S7.gif", "live_status": "is_live", "concurrent_view_count": 14, "release_timestamp": 1742872247, "icon": "https://i.ytimg.com/vi/XK4u0IDUJeE/maxresdefault.jpg"}, "S8": {"name": "PYQ NEET-JEE Live", "url": "https://raw.githubusercontent.com/JamyJones/Pastebin/main/assets/S8.gif", "live_status": "is_live", "concurrent_view_count": 19, "release_timestamp": 1742997655, "icon": "https://i.ytimg.com/vi/tva8CAtdKl8/maxresdefault.jpg"}, "S9": {"name": "Study with Sushii", "url": "https://raw.githubusercontent.com/JamyJones/Pastebin/main/assets/S9.gif", "live_status": "is_live", "concurrent_view_count": 19, "release_timestamp": 1742990861, "icon": "https://i.ytimg.com/vi/fT6-HGmiI3M/maxresdefault.jpg"}, "S10": {"name": "Alexander Mayhue", "url": "https://raw.githubusercontent.com/JamyJones/Pastebin/main/assets/S10.gif", "live_status": "is_live", "concurrent_view_count": 11, "release_timestamp": 1743016698, "icon": "https://i.ytimg.com/vi/amqSeN3Ik4A/maxresdefault.jpg"}}