{"S0": {"name": "MEDGUY", "url": "https://raw.githubusercontent.com/JamyJones/Pastebin/main/assets/S0.gif", "live_status": "is_live", "concurrent_view_count": 202, "release_timestamp": 1743750250, "icon": "https://i.ytimg.com/vi/6Ay1nBwuQ50/maxresdefault.jpg"}, "S1": {"name": "Taro's Classroom", "url": "https://raw.githubusercontent.com/JamyJones/Pastebin/main/assets/S1.gif", "live_status": "is_live", "concurrent_view_count": 143, "release_timestamp": 1743773691, "icon": "https://i.ytimg.com/vi/Z-TjIpZAd7E/maxresdefault.jpg"}, "S2": {"name": "Mohareb Study", "url": "https://raw.githubusercontent.com/JamyJones/Pastebin/main/assets/S2.gif", "live_status": "is_live", "concurrent_view_count": 124, "release_timestamp": 1743779508, "icon": "https://i.ytimg.com/vi/Mng23sUsm4g/maxresdefault.jpg"}, "S3": {"name": "PYQ NEET-JEE Live", "url": "https://raw.githubusercontent.com/JamyJones/Pastebin/main/assets/S3.gif", "live_status": "is_live", "concurrent_view_count": 42, "release_timestamp": 1743782468, "icon": "https://i.ytimg.com/vi/qJPr3MeHZIA/maxresdefault.jpg"}, "S4": {"name": "\uacf5\ubd80\ud558\ub294\uc9c0\ud638 Ziho", "url": "https://raw.githubusercontent.com/JamyJones/Pastebin/main/assets/S4.gif", "live_status": "is_live", "concurrent_view_count": 43, "release_timestamp": 1743778413, "icon": "https://i.ytimg.com/vi/0rzSXuIGpP8/maxresdefault.jpg"}, "S5": {"name": "Hilary - Study With Me", "url": "https://raw.githubusercontent.com/JamyJones/Pastebin/main/assets/S5.gif", "live_status": "is_live", "concurrent_view_count": 35, "release_timestamp": 1740999688, "icon": "https://i.ytimg.com/vi/sEGOogpgm_c/maxresdefault.jpg"}, "S6": {"name": "Ahmed\u2019s Study Zone", "url": "https://raw.githubusercontent.com/JamyJones/Pastebin/main/assets/S6.gif", "live_status": "is_live", "concurrent_view_count": 37, "release_timestamp": 1743786475, "icon": "https://i.ytimg.com/vi/SOwpiU0Ohdo/maxresdefault.jpg"}, "S7": {"name": "Tina Lin\u2019s database \ud83d\udcf7", "url": "https://raw.githubusercontent.com/JamyJones/Pastebin/main/assets/S7.gif", "live_status": "is_live", "concurrent_view_count": 31, "release_timestamp": 1742872247, "icon": "https://i.ytimg.com/vi/XK4u0IDUJeE/maxresdefault.jpg"}, "S8": {"name": "Allenite sugandh", "url": "https://raw.githubusercontent.com/JamyJones/Pastebin/main/assets/S8.gif", "live_status": "is_live", "concurrent_view_count": 25, "release_timestamp": 1743755831, "icon": "https://i.ytimg.com/vi/Ze6EuuQJSqo/hqdefault.jpg?v=67ef841d"}, "S9": {"name": "Study with Sushii", "url": "https://raw.githubusercontent.com/JamyJones/Pastebin/main/assets/S9.gif", "live_status": "is_live", "concurrent_view_count": 21, "release_timestamp": 1743772286, "icon": "https://i.ytimg.com/vi/4Xsntr6oqzg/maxresdefault.jpg"}, "S10": {"name": "Yashwant Kumar Live Study", "url": "https://raw.githubusercontent.com/JamyJones/Pastebin/main/assets/S10.gif", "live_status": "is_live", "concurrent_view_count": 26, "release_timestamp": 1743773992, "icon": "https://i.ytimg.com/vi/AtKJTZtFnK8/maxresdefault.jpg"}, "S11": {"name": "Unpredictable journey Live", "url": "https://raw.githubusercontent.com/JamyJones/Pastebin/main/assets/S11.gif", "live_status": "is_live", "concurrent_view_count": 21, "release_timestamp": 1743754041, "icon": "https://i.ytimg.com/vi/mZHPdVGQIAk/maxresdefault.jpg"}, "S12": {"name": "Ema", "url": "https://raw.githubusercontent.com/JamyJones/Pastebin/main/assets/S12.gif", "live_status": "is_live", "concurrent_view_count": 14, "release_timestamp": 1743773651, "icon": "https://i.ytimg.com/vi/yf5kZ3CGrms/maxresdefault.jpg"}, "S13": {"name": "Alexander Mayhue", "url": "https://raw.githubusercontent.com/JamyJones/Pastebin/main/assets/S13.gif", "live_status": "is_live", "concurrent_view_count": 21, "release_timestamp": 1743016698, "icon": "https://i.ytimg.com/vi/amqSeN3Ik4A/maxresdefault.jpg"}, "S14": {"name": "Made it to Medicine", "url": "https://raw.githubusercontent.com/JamyJones/Pastebin/main/assets/S14.gif", "live_status": "is_live", "concurrent_view_count": 12, "release_timestamp": 1743793421, "icon": "https://i.ytimg.com/vi/7UefYJQB5Gc/maxresdefault.jpg"}, "S15": {"name": "Twinkle - Study With Me", "url": "https://raw.githubusercontent.com/JamyJones/Pastebin/main/assets/S15.gif", "live_status": "is_live", "concurrent_view_count": 16, "release_timestamp": 1743749295, "icon": "https://i.ytimg.com/vi/6osHAnAm1nk/maxresdefault.jpg"}, "S16": {"name": "Helen Rain", "url": "https://raw.githubusercontent.com/JamyJones/Pastebin/main/assets/S16.gif", "live_status": "is_live", "concurrent_view_count": 11, "release_timestamp": 1743613223, "icon": "https://i.ytimg.com/vi/RCauL7ndxhA/maxresdefault.jpg"}, "S17": {"name": "\ud835\udcd6\ud835\udcf5\ud835\udcf8\ud835\udcfc\ud835\udcfc\ud835\udcfc\ud835\udcee\ud835\udcea", "url": "https://raw.githubusercontent.com/JamyJones/Pastebin/main/assets/S17.gif", "live_status": "is_live", "concurrent_view_count": 12, "release_timestamp": 1743758598, "icon": "https://i.ytimg.com/vi/GmzzkSpsk4o/maxresdefault.jpg"}, "S18": {"name": "Studyistic", "url": "https://raw.githubusercontent.com/JamyJones/Pastebin/main/assets/S18.gif", "live_status": "is_live", "concurrent_view_count": 14, "release_timestamp": 1732818356, "icon": "https://i.ytimg.com/vi/1OtdnQEVqG8/maxresdefault.jpg"}, "S19": {"name": "EL SAJAJ /\u0627\u0644\u0633\u062c\u0627\u062c", "url": "https://raw.githubusercontent.com/JamyJones/Pastebin/main/assets/S19.gif", "live_status": "is_live", "concurrent_view_count": 13, "release_timestamp": 1743765516, "icon": "https://i.ytimg.com/vi/dmm27fLR6t4/hqdefault.jpg?v=67efbfed"}, "S20": {"name": "MEDGIRL \ud83e\ude7a", "url": "https://raw.githubusercontent.com/JamyJones/Pastebin/main/assets/S20.gif", "live_status": "is_live", "concurrent_view_count": 8, "release_timestamp": 1742949597, "icon": "https://i.ytimg.com/vi/uF7XrVMFx4A/maxresdefault.jpg"}, "S21": {"name": "Let\u00edcia Carneiro", "url": "https://raw.githubusercontent.com/JamyJones/Pastebin/main/assets/S21.gif", "live_status": "is_live", "concurrent_view_count": 7, "release_timestamp": 1743791731, "icon": "https://i.ytimg.com/vi/ISyDBs-T5V8/maxresdefault.jpg"}, "S22": {"name": "Masked Medic", "url": "https://raw.githubusercontent.com/JamyJones/Pastebin/main/assets/S22.gif", "live_status": "is_live", "concurrent_view_count": 7, "release_timestamp": 1743784517, "icon": "https://i.ytimg.com/vi/NBiOKTpQc_A/maxresdefault.jpg"}, "S23": {"name": "Concurseira ninja", "url": "https://raw.githubusercontent.com/JamyJones/Pastebin/main/assets/S23.gif", "live_status": "is_live", "concurrent_view_count": 7, "release_timestamp": 1743790736, "icon": "https://i.ytimg.com/vi/bnifPW5fui8/maxresdefault.jpg"}, "S24": {"name": "InspireNStudy (Narendra)", "url": "https://raw.githubusercontent.com/JamyJones/Pastebin/main/assets/S24.gif", "live_status": "is_live", "concurrent_view_count": 6, "release_timestamp": 1743786986, "icon": "https://i.ytimg.com/vi/qVOp5cXBEes/hqdefault.jpg?v=67f012e3"}, "S25": {"name": "Ruya MD", "url": "https://raw.githubusercontent.com/JamyJones/Pastebin/main/assets/S25.gif", "live_status": "is_live", "concurrent_view_count": 6, "release_timestamp": 1743790159, "icon": "https://i.ytimg.com/vi/D3trJ-xX1Fc/maxresdefault.jpg"}, "S26": {"name": "\ud835\ude4a\ud835\ude4b\ud835\ude4a \u2661 \ud835\ude3c\ud835\ude4d\ud835\ude4f \u2661 \ud835\ude4e\ud835\ude4f\ud835\ude50\ud835\ude3f\ud835\ude54", "url": "https://raw.githubusercontent.com/JamyJones/Pastebin/main/assets/S26.gif", "live_status": "is_live", "concurrent_view_count": 7, "release_timestamp": 1743779796, "icon": "https://i.ytimg.com/vi/2UzGFlfQQtg/maxresdefault.jpg"}, "S27": {"name": "Sakura \ud83c\udf38", "url": "https://raw.githubusercontent.com/JamyJones/Pastebin/main/assets/S27.gif", "live_status": "is_live", "concurrent_view_count": 5, "release_timestamp": 1743789331, "icon": "https://i.ytimg.com/vi/s_VrN_mcXo0/maxresdefault.jpg"}, "S28": {"name": "Manten -\u52c9\u5f37\u30e9\u30a4\u30d6\u914d\u4fe1\u3057\u7d9a\u3051\u308b\u7537-", "url": "https://raw.githubusercontent.com/JamyJones/Pastebin/main/assets/S28.gif", "live_status": "is_live", "concurrent_view_count": 4, "release_timestamp": 1717540295, "icon": "https://i.ytimg.com/vi/pp2AOG_QkRY/maxresdefault.jpg"}, "S29": {"name": "STUDY BO", "url": "https://raw.githubusercontent.com/JamyJones/Pastebin/main/assets/S29.gif", "live_status": "is_live", "concurrent_view_count": 4, "release_timestamp": 1742997156, "icon": "https://i.ytimg.com/vi/D1a2aHnNU7Q/maxresdefault.jpg"}, "S30": {"name": "Nagesh gaud live", "url": "https://raw.githubusercontent.com/JamyJones/Pastebin/main/assets/S30.gif", "live_status": "is_live", "concurrent_view_count": 4, "release_timestamp": 1743786856, "icon": "https://i.ytimg.com/vi/ydipLakHu5o/maxresdefault.jpg"}, "S31": {"name": "just-Nico", "url": "https://raw.githubusercontent.com/JamyJones/Pastebin/main/assets/S31.gif", "live_status": "is_live", "concurrent_view_count": 3, "release_timestamp": 1741686092, "icon": "https://i.ytimg.com/vi/SOGq0eUD2QY/maxresdefault.jpg"}, "S32": {"name": "Maths with Lakshya", "url": "https://raw.githubusercontent.com/JamyJones/Pastebin/main/assets/S32.gif", "live_status": "is_live", "concurrent_view_count": 1, "release_timestamp": 1743781506, "icon": "https://i.ytimg.com/vi/9R-Oz8XYs4s/maxresdefault.jpg"}, "S33": {"name": "Pankaj Lakhani", "url": "https://raw.githubusercontent.com/JamyJones/Pastebin/main/assets/S33.gif", "live_status": "is_live", "concurrent_view_count": 4, "release_timestamp": 1743791485, "icon": "https://i.ytimg.com/vi/J_FulBg91qw/maxresdefault.jpg"}, "S34": {"name": "\u5922\u5e7b\u97f3\u5883", "url": "https://raw.githubusercontent.com/JamyJones/Pastebin/main/assets/S34.gif", "live_status": "is_live", "concurrent_view_count": 2, "release_timestamp": 1742600036, "icon": "https://i.ytimg.com/vi/kD5Mp1FQ7Kw/maxresdefault.jpg"}, "S35": {"name": "Ranthambhore Study Express \ud83d\udcda\ud83d\ude89", "url": "https://raw.githubusercontent.com/JamyJones/Pastebin/main/assets/S35.gif", "live_status": "is_live", "concurrent_view_count": 5, "release_timestamp": 1743776616, "icon": "https://i.ytimg.com/vi/pt7P2Y6O9pk/maxresdefault.jpg"}, "S36": {"name": "MedMindsetDr", "url": "https://raw.githubusercontent.com/JamyJones/Pastebin/main/assets/S36.gif", "live_status": "is_live", "concurrent_view_count": 1, "release_timestamp": 1743760235, "icon": "https://i.ytimg.com/vi/S5OA5M4E9yk/maxresdefault.jpg"}, "S37": {"name": "The Kozzy Bee", "url": "https://raw.githubusercontent.com/JamyJones/Pastebin/main/assets/S37.gif", "live_status": "is_live", "concurrent_view_count": 2, "release_timestamp": 1743789067, "icon": "https://i.ytimg.com/vi/pt9yM6hWfPo/hqdefault.jpg?v=67f01be2"}, "S38": {"name": "Ajay is busy in study", "url": "https://raw.githubusercontent.com/JamyJones/Pastebin/main/assets/S38.gif", "live_status": "is_live", "concurrent_view_count": 1, "release_timestamp": 1743785713, "icon": "https://i.ytimg.com/vi/F3heXgHcCgg/hqdefault.jpg?v=67f00ee4"}, "S39": {"name": "Santoshi official", "url": "https://raw.githubusercontent.com/JamyJones/Pastebin/main/assets/S39.gif", "live_status": "is_live", "concurrent_view_count": 2, "release_timestamp": 1743788647, "icon": "https://i.ytimg.com/vi/sfLkzNUAGJo/hqdefault.jpg?v=67f01a45"}, "S40": {"name": "Shaurya Swarup", "url": "https://raw.githubusercontent.com/JamyJones/Pastebin/main/assets/S40.gif", "live_status": "is_live", "concurrent_view_count": 2, "release_timestamp": 1743781638, "icon": "https://i.ytimg.com/vi/uhfkFYL67RY/maxresdefault.jpg"}, "S41": {"name": "Study with Shubhu live", "url": "https://raw.githubusercontent.com/JamyJones/Pastebin/main/assets/S41.gif", "live_status": "is_live", "concurrent_view_count": 5, "release_timestamp": 1743775520, "icon": "https://i.ytimg.com/vi/by7EESQ3RjA/hqdefault.jpg?v=67efe6ed"}, "S42": {"name": "Study with Micah", "url": "https://raw.githubusercontent.com/JamyJones/Pastebin/main/assets/S42.gif", "live_status": "is_live", "concurrent_view_count": 2, "release_timestamp": 1743793554, "icon": "https://i.ytimg.com/vi/3IMMur-onIk/maxresdefault.jpg"}, "S43": {"name": "Pranuthi", "url": "https://raw.githubusercontent.com/JamyJones/Pastebin/main/assets/S43.gif", "live_status": "is_live", "concurrent_view_count": 1, "release_timestamp": 1743777234, "icon": "https://i.ytimg.com/vi/QOAp133DArs/hqdefault.jpg?v=67eff5dc"}, "S44": {"name": "Happy Melody", "url": "https://raw.githubusercontent.com/JamyJones/Pastebin/main/assets/S44.gif", "live_status": "is_live", "concurrent_view_count": 1, "release_timestamp": 1743393627, "icon": "https://i.ytimg.com/vi/ejVdR9yGvjw/maxresdefault.jpg"}, "S45": {"name": "Estude comigo Paula", "url": "https://raw.githubusercontent.com/JamyJones/Pastebin/main/assets/S45.gif", "live_status": "is_live", "concurrent_view_count": 4, "release_timestamp": 1743792706, "icon": "https://i.ytimg.com/vi/4_EiUBAcbEk/maxresdefault.jpg"}, "S46": {"name": "Keyvan Parto", "url": "https://raw.githubusercontent.com/JamyJones/Pastebin/main/assets/S46.gif", "live_status": "is_live", "concurrent_view_count": 1, "release_timestamp": 1743756984, "icon": "https://i.ytimg.com/vi/6BHPReJXGg8/hqdefault.jpg?v=67ef9eaa"}, "S47": {"name": "Study Aesthetic - Shruti Singh", "url": "https://raw.githubusercontent.com/JamyJones/Pastebin/main/assets/S47.gif", "live_status": "is_live", "concurrent_view_count": 1, "release_timestamp": 1743787551, "icon": "https://i.ytimg.com/vi/Ea-XFztqut4/maxresdefault.jpg"}, "S48": {"name": "Study with Me", "url": "https://raw.githubusercontent.com/JamyJones/Pastebin/main/assets/S48.gif", "live_status": "is_live", "concurrent_view_count": 1, "release_timestamp": 1743609975, "icon": "https://i.ytimg.com/vi/KSGJgCANMpk/maxresdefault.jpg"}, "S50": {"name": "A2A Journey Diary", "url": "https://raw.githubusercontent.com/JamyJones/Pastebin/main/assets/S50.gif", "live_status": "is_live", "concurrent_view_count": 1, "release_timestamp": 1743791466, "icon": "https://i.ytimg.com/vi/eV97iDyRnDs/maxresdefault.jpg"}, "S51": {"name": "Andree", "url": "https://raw.githubusercontent.com/JamyJones/Pastebin/main/assets/S51.gif", "live_status": "is_live", "concurrent_view_count": 1, "release_timestamp": 1743793514, "icon": "https://i.ytimg.com/vi/zpHJltWYcPs/maxresdefault.jpg"}, "S52": {"name": "estudiandoenlosvolcanes", "url": "https://raw.githubusercontent.com/JamyJones/Pastebin/main/assets/S52.gif", "live_status": "is_live", "concurrent_view_count": 1, "release_timestamp": 1743783562, "icon": "https://i.ytimg.com/vi/rZNBGk3kbsU/maxresdefault.jpg"}, "S53": {"name": "Dropper to Doctor \ud83e\ude7a", "url": "https://raw.githubusercontent.com/JamyJones/Pastebin/main/assets/S53.gif", "live_status": "is_live", "concurrent_view_count": 1, "release_timestamp": 1743781323, "icon": "https://i.ytimg.com/vi/QOCV7YSnMak/hqdefault.jpg?v=67effe64"}, "S54": {"name": "MedicoChild", "url": "https://raw.githubusercontent.com/JamyJones/Pastebin/main/assets/S54.gif", "live_status": "is_live", "concurrent_view_count": 1, "release_timestamp": 1743779776, "icon": "https://i.ytimg.com/vi/w3K62fs5EWc/maxresdefault.jpg"}, "S55": {"name": "Doc_anshu1908 vlogs", "url": "https://raw.githubusercontent.com/JamyJones/Pastebin/main/assets/S55.gif", "live_status": "is_live", "concurrent_view_count": 1, "release_timestamp": 1743787305, "icon": "https://i.ytimg.com/vi/GSEAMEAIlRo/maxresdefault.jpg"}, "S56": {"name": "Ascomany", "url": "https://raw.githubusercontent.com/JamyJones/Pastebin/main/assets/S56.gif", "live_status": "is_live", "concurrent_view_count": 1, "release_timestamp": 1743793189, "icon": "https://i.ytimg.com/vi/nxqQa4VLjpU/maxresdefault.jpg"}, "S57": {"name": "NEET Live Study Hub", "url": "https://raw.githubusercontent.com/JamyJones/Pastebin/main/assets/S57.gif", "live_status": "is_live", "concurrent_view_count": 1, "release_timestamp": 1743742262, "icon": "https://i.ytimg.com/vi/O_I84giMy_Y/maxresdefault.jpg"}, "S58": {"name": "STUDY WITH AMAN", "url": "https://raw.githubusercontent.com/JamyJones/Pastebin/main/assets/S58.gif", "live_status": "is_live", "concurrent_view_count": 1, "release_timestamp": 1743769816, "icon": "https://i.ytimg.com/vi/ccKClcv-GrE/maxresdefault.jpg"}}